brain_games/__init__.py
brain_games/cli.py
brain_games/games/__init__.py
brain_games/games/brain_calc.py
brain_games/games/brain_even.py
brain_games/games/brain_games.py
brain_games/games/brain_gcd.py
brain_games/games/brain_prime.py
brain_games/games/brain_progression.py
brain_games/scripts/__init__.py
ruffury_hexlet_code-0.1.0.dist-info/entry_points.txt
ruffury_hexlet_code-0.1.0.dist-info/WHEEL
ruffury_hexlet_code-0.1.0.dist-info/METADATA
ruffury_hexlet_code-0.1.0.dist-info/RECORD
